automate_mts/__init__.py
automate_mts/__main__.py
change_extension/__init__.py
change_extension/__main__.py
gen_doc/__init__.py
gen_doc/__main__.py
gen_doc/automate.py
gen_doc/change.py
gen_doc/prepare_pdfs.py
gen_doc/publish.py
gendoc/__init__.py
gendoc/__main__.py
mts_upload/__init__.py
mts_upload/__main__.py
mts_upload/old_main.py
mts_gendoc_cobol-1.1.8.dist-info/METADATA
mts_gendoc_cobol-1.1.8.dist-info/WHEEL
mts_gendoc_cobol-1.1.8.dist-info/entry_points.txt
mts_gendoc_cobol-1.1.8.dist-info/top_level.txt
mts_gendoc_cobol-1.1.8.dist-info/RECORD
