Metadata-Version: 2.4
Name: mts-gendoc-cobol
Version: 1.1.8
Summary: A set of CLI helpers for COBOL doc generation and file utilities.
Author: Ben Bastianelli
Author-email: benbastianelli@gmail.com
Classifier: Programming Language :: Python :: 3
Classifier: Operating System :: OS Independent
Requires-Python: >=3.6
Requires-Dist: requests>=2.0
Requires-Dist: Markdown>=3.0
Requires-Dist: tqdm>=4.0
Dynamic: author
Dynamic: author-email
Dynamic: classifier
Dynamic: requires-dist
Dynamic: requires-python
Dynamic: summary
